Shelly_Statistic_flawas/__init__.py
Shelly_Statistic_flawas/main.py
shelly_statistic_flawas-0.0.1.dist-info/METADATA
shelly_statistic_flawas-0.0.1.dist-info/WHEEL
shelly_statistic_flawas-0.0.1.dist-info/licenses/LICENSE
shelly_statistic_flawas-0.0.1.dist-info/RECORD
